toolboxv2/__init__.py
toolboxv2/__main__.py
toolboxv2/mcp_server_leg.py
toolboxv2/setup_helper.py
toolboxv2/flows/__init__.py
toolboxv2/flows/auto_git_commit.py
toolboxv2/flows/bg.py
toolboxv2/flows/bgws.py
toolboxv2/flows/bottelUp.py
toolboxv2/flows/chain.py
toolboxv2/flows/core0.py
toolboxv2/flows/docker.py
toolboxv2/flows/folder_to_graph_query.py
toolboxv2/flows/idle.py
toolboxv2/flows/isaa_cli.py
toolboxv2/flows/isaa_cliv2.py
toolboxv2/flows/minicli.py
toolboxv2/flows/story_generator.py
toolboxv2/flows/univ.py
toolboxv2/flows/vad_talk.py
toolboxv2/mcp_server/__init__.py
toolboxv2/mcp_server/__main__.py
toolboxv2/mcp_server/flow_handlers.py
toolboxv2/mcp_server/flow_manager.py
toolboxv2/mcp_server/http_transport.py
toolboxv2/mcp_server/managers.py
toolboxv2/mcp_server/models.py
toolboxv2/mcp_server/server.py
toolboxv2/mcp_server/workers.py
toolboxv2/mods/Canvas.py
toolboxv2/mods/ChatModule.py
toolboxv2/mods/CodeVerification.py
toolboxv2/mods/CounterTracker.py
toolboxv2/mods/FileWidget.py
toolboxv2/mods/MinimalHtml.py
toolboxv2/mods/P2PRPCClient.py
toolboxv2/mods/P2PRPCServer.py
toolboxv2/mods/PasswordManager.py
toolboxv2/mods/ProcessManager.py
toolboxv2/mods/SchedulerManager.py
toolboxv2/mods/SocketManager.py
toolboxv2/mods/TTS.py
toolboxv2/mods/UltimateTTT.py
toolboxv2/mods/WebSocketManager.py
toolboxv2/mods/__init__.py
toolboxv2/mods/cli_functions.py
toolboxv2/mods/helper.py
toolboxv2/mods/talk.py
toolboxv2/mods/welcome.py
toolboxv2/mods/CloudM/AdminDashboard.py
toolboxv2/mods/CloudM/AuthClerk.py
toolboxv2/mods/CloudM/AuthManager.py
toolboxv2/mods/CloudM/DashboardAPI.py
toolboxv2/mods/CloudM/LogInSystem.py
toolboxv2/mods/CloudM/ModManager.py
toolboxv2/mods/CloudM/ModManager_tests.py
toolboxv2/mods/CloudM/UserAccountManager.py
toolboxv2/mods/CloudM/UserDashboard.py
toolboxv2/mods/CloudM/UserDataAPI.py
toolboxv2/mods/CloudM/UserInstances.py
toolboxv2/mods/CloudM/__init__.py
toolboxv2/mods/CloudM/email_services.py
toolboxv2/mods/CloudM/extras.py
toolboxv2-0.1.25.dist-info/licenses/AUTHORS.rst
toolboxv2-0.1.25.dist-info/licenses/LICENSE
toolboxv2-0.1.25.dist-info/METADATA
toolboxv2-0.1.25.dist-info/WHEEL
toolboxv2-0.1.25.dist-info/dependency_links.txt
toolboxv2-0.1.25.dist-info/entry_points.txt
toolboxv2-0.1.25.dist-info/top_level.txt
toolboxv2-0.1.25.dist-info/RECORD
