Metadata-Version: 2.4
Name: toolboxv2
Version: 0.1.25
Summary: Add your description here
Home-page: https://github.com/MarkinHaus/ToolBoxV2
Author: Markin Hausmanns
Author-email: Markinhausmanns@gmail.com
Requires-Python: >=3.10
License-File: LICENSE
License-File: AUTHORS.rst
Requires-Dist: aiohttp>=3.12.15
Requires-Dist: cachetools>=5.5.2
Requires-Dist: cryptography>=45.0.7
Requires-Dist: ipython>=8.5.0
Requires-Dist: networkx>=3.4.2
Requires-Dist: numpy>=2.2.6
Requires-Dist: packaging>=24.2
Requires-Dist: pyjwt>=2.10.1
Requires-Dist: python-dotenv>=1.0.1
Requires-Dist: pyyaml>=6.0.2
Requires-Dist: redis>=6.4.0
Requires-Dist: toml>=0.10.2
Requires-Dist: tqdm>=4.67.1
Requires-Dist: watchfiles>=1.0.4
Requires-Dist: webauthn>=2.5.1
Requires-Dist: schedule>=1.2.2
Requires-Dist: websockets>=15.0.1
Requires-Dist: langdetect>=1.0.9
Requires-Dist: google-auth-oauthlib>=1.2.2
Requires-Dist: google-api-python-client>=2.179.0
Requires-Dist: readchar>=4.2.1
Requires-Dist: dateparser>=1.2.2
Requires-Dist: bottle>=0.13.4
Requires-Dist: xmltodict>=0.14.2
Requires-Dist: traitlets>=5.14.3
Requires-Dist: prompt-toolkit>=3.0.52
Requires-Dist: gitpython>=3.1.45
Requires-Dist: rich>=14.1.0
Requires-Dist: pytz>=2025.2
Requires-Dist: python-dateutil>=2.9.0.post0
Requires-Dist: starlette>=0.47.3
Requires-Dist: urllib3>=2.5.0
Requires-Dist: psutil>=7.0.0
Requires-Dist: dill>=0.3.8
Requires-Dist: icalendar>=6.3.1
Requires-Dist: mcp[cli]>=1.13.1
Requires-Dist: pydantic[email]>=2.11.7
Requires-Dist: clerk-backend-api>=4.0.0
Requires-Dist: minio>=7.2.20
Requires-Dist: waitress>=3.0.2
Requires-Dist: pyzmq>=27.1.0
Requires-Dist: aiohttp-cors>=0.8.1
Provides-Extra: isaa
Requires-Dist: beautifulsoup4>=4.12.0; extra == "isaa"
Requires-Dist: langchain-core>=0.1.20; extra == "isaa"
Requires-Dist: litellm~=1.74.14; extra == "isaa"
Requires-Dist: networkx>=3.1; extra == "isaa"
Requires-Dist: pydantic>=2.5.0; extra == "isaa"
Requires-Dist: groq>=0.31.0; extra == "isaa"
Requires-Dist: requests>=2.31.0; extra == "isaa"
Requires-Dist: tiktoken>=0.5.0; extra == "isaa"
Requires-Dist: tqdm>=4.66.0; extra == "isaa"
Requires-Dist: pypdf2>=3.0.1; extra == "isaa"
Requires-Dist: nest-asyncio>=1.5.0; extra == "isaa"
Requires-Dist: schedule>=1.2.0; extra == "isaa"
Requires-Dist: pyvis>=0.3.0; extra == "isaa"
Requires-Dist: redis>=5.0.0; extra == "isaa"
Requires-Dist: python-a2a[all]>=0.5.1; extra == "isaa"
Requires-Dist: mcp>=1.6.0; extra == "isaa"
Requires-Dist: google-cloud-aiplatform>=1.38.0; extra == "isaa"
Requires-Dist: pyyaml>=6.0; extra == "isaa"
Requires-Dist: docker>=7.0.0; extra == "isaa"
Requires-Dist: hnswlib>=0.8.0; extra == "isaa"
Requires-Dist: inquirer>=3.4.1; extra == "isaa"
Requires-Dist: tenacity>=9.1.2; extra == "isaa"
Requires-Dist: opentelemetry-api>=1.36.0; extra == "isaa"
Requires-Dist: opentelemetry-sdk>=1.36.0; extra == "isaa"
Requires-Dist: jinja2>=3.1.6; extra == "isaa"
Requires-Dist: playwright>=1.55.0; extra == "isaa"
Requires-Dist: markdown2>=2.5.3; extra == "isaa"
Requires-Dist: beautifulsoup4>=4.13.3; extra == "isaa"
Requires-Dist: html2text>=2025.4.15; extra == "isaa"
Requires-Dist: chardet>=5.2.0; extra == "isaa"
Requires-Dist: faiss-cpu>=1.12.0; extra == "isaa"
Requires-Dist: langchain-community>=0.3.29; extra == "isaa"
Dynamic: author
Dynamic: author-email
Dynamic: home-page
Dynamic: license-file
Dynamic: requires-python
